termii_sdk/__init__.py
termii_sdk/core.py
termii_sdk/error.py
termii_sdk/insights_api.py
termii_sdk/messaging_api.py
termii_sdk/token_api.py
termii_sdk-1.0.dist-info/LICENSE
termii_sdk-1.0.dist-info/METADATA
termii_sdk-1.0.dist-info/WHEEL
termii_sdk-1.0.dist-info/top_level.txt
termii_sdk-1.0.dist-info/RECORD
