Metadata-Version: 2.1
Name: termii-sdk
Version: 1.0
Summary: The `termii_sdk` is a Python package that facilitates seamless integration with the Termii API, empowering developers to send SMS, voice, and email messages within their applications.
Home-page: UNKNOWN
License: UNKNOWN
Platform: UNKNOWN
License-File: LICENSE
Requires-Dist: requests
